Metadata-Version: 2.1
Name: IPProcessor
Version: 0.1
Summary: Process any image and replaces each color to it is more similar from a selected palette
Home-page: https://github.com/JGuillenY/ImagePixelProcessor
Download-URL: https://github.com/JGuillenY/ImagePixelProcessor/archive/refs/tags/0.1.tar.gz
Author: Jesús Guillén
Author-email: jesus.guilleny@gmail.com
License: MIT
Keywords: PIXEL,IMAGE,PROCESSOR,PNG
Classifier: Development Status :: 3 - Alpha
Classifier: Intended Audience :: Developers
Classifier: Topic :: Software Development :: Build Tools
Classifier: License :: OSI Approved :: MIT License
Classifier: Programming Language :: Python :: 3
Classifier: Programming Language :: Python :: 3.4
Classifier: Programming Language :: Python :: 3.5
Classifier: Programming Language :: Python :: 3.6
Classifier: Programming Language :: Python :: 3.7
Classifier: Programming Language :: Python :: 3.8
Classifier: Programming Language :: Python :: 3.9
Classifier: Programming Language :: Python :: 3.10
License-File: LICENSE.txt
